odoo/addons/shopfloor_dangerous_goods/README.rst
odoo/addons/shopfloor_dangerous_goods/__init__.py
odoo/addons/shopfloor_dangerous_goods/__manifest__.py
odoo/addons/shopfloor_dangerous_goods/actions/__init__.py
odoo/addons/shopfloor_dangerous_goods/actions/data.py
odoo/addons/shopfloor_dangerous_goods/actions/schema.py
odoo/addons/shopfloor_dangerous_goods/i18n/it.po
odoo/addons/shopfloor_dangerous_goods/i18n/shopfloor_dangerous_goods.pot
odoo/addons/shopfloor_dangerous_goods/readme/CONTRIBUTORS.md
odoo/addons/shopfloor_dangerous_goods/readme/DESCRIPTION.md
odoo/addons/shopfloor_dangerous_goods/static/description/icon.png
odoo/addons/shopfloor_dangerous_goods/static/description/index.html
odoo/addons/shopfloor_dangerous_goods/tests/__init__.py
odoo/addons/shopfloor_dangerous_goods/tests/test_actions_data.py
odoo_addon_shopfloor_dangerous_goods-18.0.1.0.1.dist-info/METADATA
odoo_addon_shopfloor_dangerous_goods-18.0.1.0.1.dist-info/WHEEL
odoo_addon_shopfloor_dangerous_goods-18.0.1.0.1.dist-info/top_level.txt
odoo_addon_shopfloor_dangerous_goods-18.0.1.0.1.dist-info/RECORD
