Metadata-Version: 2.1
Name: odoo-addon-shopfloor_dangerous_goods
Version: 18.0.1.0.1
Requires-Python: >=3.10
Requires-Dist: odoo-addon-shopfloor==18.0.*
Requires-Dist: odoo-addon-stock_dangerous_goods==18.0.*
Requires-Dist: odoo==18.0.*
Summary: Glue Module Between Shopfloor and Stock Dangerous Goods
Home-page: https://github.com/OCA/stock-logistics-shopfloor
License: AGPL-3
Author: Camptocamp, Odoo Community Association (OCA)
Author-email: support@odoo-community.org
Classifier: Programming Language :: Python
Classifier: Framework :: Odoo
Classifier: Framework :: Odoo :: 18.0
Classifier: License :: OSI Approved :: GNU Affero General Public License v3
Classifier: Development Status :: 3 - Alpha
